{
    "isPlanted": true,
    "minYield": 2,
    "maxYield": 5,
    "currentStageNeedsWater": false,
    "currentStageProgress": 4,
    "minutesSinceLastStage": 0.0,
    "numStagesWatered": 0,
    "itemAssetName": "Pecha berry",
    "berryItem": {
        "instanceID": 25346
    },
    "treeIndex": 5,
    "minutesPerStage": 45,
    "spriteData": [
        {
            "growthStageSprites": [
                {
                    "instanceID": 31082
                },
                {
                    "instanceID": 31082
                }
            ],
            "growthStageNumber": 0
        },
        {
            "growthStageSprites": [
                {
                    "instanceID": 31084
                },
                {
                    "instanceID": 31086
                }
            ],
            "growthStageNumber": 1
        },
        {
            "growthStageSprites": [
                {
                    "instanceID": 31650
                },
                {
                    "instanceID": 31652
                }
            ],
            "growthStageNumber": 2
        },
        {
            "growthStageSprites": [
                {
                    "instanceID": 31654
                },
                {
                    "instanceID": 31656
                }
            ],
            "growthStageNumber": 3
        },
        {
            "growthStageSprites": [
                {
                    "instanceID": 31658
                },
                {
                    "instanceID": 31660
                }
            ],
            "growthStageNumber": 4
        }
    ],
    "lastLogin": "2026-02-05T10:50:59.8992240+02:00"
}