{
    "isPlanted": true,
    "minYield": 2,
    "maxYield": 5,
    "currentStageNeedsWater": false,
    "currentStageProgress": 4,
    "minutesSinceLastStage": 0.0,
    "numStagesWatered": 0,
    "itemAssetName": "Chesto berry",
    "berryItem": {
        "instanceID": 26410
    },
    "treeIndex": 9,
    "minutesPerStage": 45,
    "spriteData": [
        {
            "growthStageSprites": [
                {
                    "instanceID": 32770
                },
                {
                    "instanceID": 32770
                }
            ],
            "growthStageNumber": 0
        },
        {
            "growthStageSprites": [
                {
                    "instanceID": 32772
                },
                {
                    "instanceID": 32774
                }
            ],
            "growthStageNumber": 1
        },
        {
            "growthStageSprites": [
                {
                    "instanceID": 32776
                },
                {
                    "instanceID": 32778
                }
            ],
            "growthStageNumber": 2
        },
        {
            "growthStageSprites": [
                {
                    "instanceID": 32780
                },
                {
                    "instanceID": 32782
                }
            ],
            "growthStageNumber": 3
        },
        {
            "growthStageSprites": [
                {
                    "instanceID": 32784
                },
                {
                    "instanceID": 32786
                }
            ],
            "growthStageNumber": 4
        }
    ],
    "lastLogin": "2026-01-04T14:07:48.1484460+02:00"
}