{
    "isPlanted": true,
    "minYield": 2,
    "maxYield": 5,
    "currentStageNeedsWater": false,
    "currentStageProgress": 4,
    "minutesSinceLastStage": 0.0,
    "numStagesWatered": 0,
    "itemAssetName": "Cherri berry",
    "berryItem": {
        "instanceID": 26308
    },
    "treeIndex": 10,
    "minutesPerStage": 45,
    "spriteData": [
        {
            "growthStageSprites": [
                {
                    "instanceID": 32300
                },
                {
                    "instanceID": 32300
                }
            ],
            "growthStageNumber": 0
        },
        {
            "growthStageSprites": [
                {
                    "instanceID": 32302
                },
                {
                    "instanceID": 32304
                }
            ],
            "growthStageNumber": 1
        },
        {
            "growthStageSprites": [
                {
                    "instanceID": 32698
                },
                {
                    "instanceID": 32700
                }
            ],
            "growthStageNumber": 2
        },
        {
            "growthStageSprites": [
                {
                    "instanceID": 32702
                },
                {
                    "instanceID": 32704
                }
            ],
            "growthStageNumber": 3
        },
        {
            "growthStageSprites": [
                {
                    "instanceID": 32706
                },
                {
                    "instanceID": 32708
                }
            ],
            "growthStageNumber": 4
        }
    ],
    "lastLogin": "2025-11-03T13:21:46.2807670+02:00"
}