{
    "isPlanted": true,
    "minYield": 2,
    "maxYield": 5,
    "currentStageNeedsWater": false,
    "currentStageProgress": 4,
    "minutesSinceLastStage": 0.0,
    "numStagesWatered": 0,
    "itemAssetName": "Pecha berry",
    "berryItem": {
        "instanceID": 25330
    },
    "treeIndex": 5,
    "minutesPerStage": 45,
    "spriteData": [
        {
            "growthStageSprites": [
                {
                    "instanceID": 32312
                },
                {
                    "instanceID": 32312
                }
            ],
            "growthStageNumber": 0
        },
        {
            "growthStageSprites": [
                {
                    "instanceID": 32314
                },
                {
                    "instanceID": 32316
                }
            ],
            "growthStageNumber": 1
        },
        {
            "growthStageSprites": [
                {
                    "instanceID": 33000
                },
                {
                    "instanceID": 33002
                }
            ],
            "growthStageNumber": 2
        },
        {
            "growthStageSprites": [
                {
                    "instanceID": 33004
                },
                {
                    "instanceID": 33006
                }
            ],
            "growthStageNumber": 3
        },
        {
            "growthStageSprites": [
                {
                    "instanceID": 33008
                },
                {
                    "instanceID": 33010
                }
            ],
            "growthStageNumber": 4
        }
    ],
    "lastLogin": "2026-02-18T09:46:51.2936690+02:00"
}