{
    "isPlanted": true,
    "minYield": 1,
    "maxYield": 5,
    "currentStageNeedsWater": false,
    "currentStageProgress": 4,
    "minutesSinceLastStage": 0.0,
    "numStagesWatered": 0,
    "itemAssetName": "Kelpsy berry",
    "berryItem": {
        "instanceID": 25324
    },
    "treeIndex": 31,
    "minutesPerStage": 180,
    "spriteData": [
        {
            "growthStageSprites": [
                {
                    "instanceID": 32608
                },
                {
                    "instanceID": 32608
                }
            ],
            "growthStageNumber": 0
        },
        {
            "growthStageSprites": [
                {
                    "instanceID": 32610
                },
                {
                    "instanceID": 32612
                }
            ],
            "growthStageNumber": 1
        },
        {
            "growthStageSprites": [
                {
                    "instanceID": 32960
                },
                {
                    "instanceID": 32962
                }
            ],
            "growthStageNumber": 2
        },
        {
            "growthStageSprites": [
                {
                    "instanceID": 32964
                },
                {
                    "instanceID": 32966
                }
            ],
            "growthStageNumber": 3
        },
        {
            "growthStageSprites": [
                {
                    "instanceID": 32968
                },
                {
                    "instanceID": 32970
                }
            ],
            "growthStageNumber": 4
        }
    ],
    "lastLogin": "2025-12-02T11:59:47.0166020+02:00"
}