{
    "isPlanted": true,
    "minYield": 1,
    "maxYield": 5,
    "currentStageNeedsWater": false,
    "currentStageProgress": 4,
    "minutesSinceLastStage": 0.0,
    "numStagesWatered": 0,
    "itemAssetName": "Tamato berry",
    "berryItem": {
        "instanceID": 26786
    },
    "treeIndex": 2,
    "minutesPerStage": 180,
    "spriteData": [
        {
            "growthStageSprites": [
                {
                    "instanceID": 32890
                },
                {
                    "instanceID": 32890
                }
            ],
            "growthStageNumber": 0
        },
        {
            "growthStageSprites": [
                {
                    "instanceID": 32892
                },
                {
                    "instanceID": 32894
                }
            ],
            "growthStageNumber": 1
        },
        {
            "growthStageSprites": [
                {
                    "instanceID": 33252
                },
                {
                    "instanceID": 33254
                }
            ],
            "growthStageNumber": 2
        },
        {
            "growthStageSprites": [
                {
                    "instanceID": 33256
                },
                {
                    "instanceID": 33258
                }
            ],
            "growthStageNumber": 3
        },
        {
            "growthStageSprites": [
                {
                    "instanceID": 33260
                },
                {
                    "instanceID": 33262
                }
            ],
            "growthStageNumber": 4
        }
    ],
    "lastLogin": "2026-01-22T20:27:53.5540310+02:00"
}