{
    "isPlanted": true,
    "minYield": 1,
    "maxYield": 5,
    "currentStageNeedsWater": false,
    "currentStageProgress": 4,
    "minutesSinceLastStage": 0.0,
    "numStagesWatered": 0,
    "itemAssetName": "Grepa berry",
    "berryItem": {
        "instanceID": 26358
    },
    "treeIndex": 30,
    "minutesPerStage": 180,
    "spriteData": [
        {
            "growthStageSprites": [
                {
                    "instanceID": 32616
                },
                {
                    "instanceID": 32616
                }
            ],
            "growthStageNumber": 0
        },
        {
            "growthStageSprites": [
                {
                    "instanceID": 32618
                },
                {
                    "instanceID": 32620
                }
            ],
            "growthStageNumber": 1
        },
        {
            "growthStageSprites": [
                {
                    "instanceID": 32640
                },
                {
                    "instanceID": 32642
                }
            ],
            "growthStageNumber": 2
        },
        {
            "growthStageSprites": [
                {
                    "instanceID": 32644
                },
                {
                    "instanceID": 32646
                }
            ],
            "growthStageNumber": 3
        },
        {
            "growthStageSprites": [
                {
                    "instanceID": 32648
                },
                {
                    "instanceID": 32650
                }
            ],
            "growthStageNumber": 4
        }
    ],
    "lastLogin": "2025-12-03T17:00:55.9107170+02:00"
}