{
    "isPlanted": true,
    "minYield": 2,
    "maxYield": 5,
    "currentStageNeedsWater": false,
    "currentStageProgress": 4,
    "minutesSinceLastStage": 0.0,
    "numStagesWatered": 0,
    "itemAssetName": "Oran berry",
    "berryItem": {
        "instanceID": 26172
    },
    "treeIndex": 11,
    "minutesPerStage": 60,
    "spriteData": [
        {
            "growthStageSprites": [
                {
                    "instanceID": 33044
                },
                {
                    "instanceID": 33044
                }
            ],
            "growthStageNumber": 0
        },
        {
            "growthStageSprites": [
                {
                    "instanceID": 33046
                },
                {
                    "instanceID": 33048
                }
            ],
            "growthStageNumber": 1
        },
        {
            "growthStageSprites": [
                {
                    "instanceID": 33192
                },
                {
                    "instanceID": 33194
                }
            ],
            "growthStageNumber": 2
        },
        {
            "growthStageSprites": [
                {
                    "instanceID": 33196
                },
                {
                    "instanceID": 33198
                }
            ],
            "growthStageNumber": 3
        },
        {
            "growthStageSprites": [
                {
                    "instanceID": 33200
                },
                {
                    "instanceID": 33202
                }
            ],
            "growthStageNumber": 4
        }
    ],
    "lastLogin": "2026-01-29T14:48:12.6559150+02:00"
}