{
    "isPlanted": true,
    "minYield": 1,
    "maxYield": 5,
    "currentStageNeedsWater": false,
    "currentStageProgress": 4,
    "minutesSinceLastStage": 0.0,
    "numStagesWatered": 0,
    "itemAssetName": "Kelpsy berry",
    "berryItem": {
        "instanceID": 26716
    },
    "treeIndex": 15,
    "minutesPerStage": 180,
    "spriteData": [
        {
            "growthStageSprites": [
                {
                    "instanceID": 32518
                },
                {
                    "instanceID": 32518
                }
            ],
            "growthStageNumber": 0
        },
        {
            "growthStageSprites": [
                {
                    "instanceID": 32520
                },
                {
                    "instanceID": 32522
                }
            ],
            "growthStageNumber": 1
        },
        {
            "growthStageSprites": [
                {
                    "instanceID": 32854
                },
                {
                    "instanceID": 32856
                }
            ],
            "growthStageNumber": 2
        },
        {
            "growthStageSprites": [
                {
                    "instanceID": 32858
                },
                {
                    "instanceID": 32860
                }
            ],
            "growthStageNumber": 3
        },
        {
            "growthStageSprites": [
                {
                    "instanceID": 32862
                },
                {
                    "instanceID": 32864
                }
            ],
            "growthStageNumber": 4
        }
    ],
    "lastLogin": "2026-04-12T11:58:43.3789630+02:00"
}