{
    "isPlanted": true,
    "minYield": 2,
    "maxYield": 5,
    "currentStageNeedsWater": false,
    "currentStageProgress": 4,
    "minutesSinceLastStage": 0.0,
    "numStagesWatered": 0,
    "itemAssetName": "Aspear berry",
    "berryItem": {
        "instanceID": 26392
    },
    "treeIndex": 3,
    "minutesPerStage": 45,
    "spriteData": [
        {
            "growthStageSprites": [
                {
                    "instanceID": 31004
                },
                {
                    "instanceID": 31004
                }
            ],
            "growthStageNumber": 0
        },
        {
            "growthStageSprites": [
                {
                    "instanceID": 31006
                },
                {
                    "instanceID": 31008
                }
            ],
            "growthStageNumber": 1
        },
        {
            "growthStageSprites": [
                {
                    "instanceID": 31562
                },
                {
                    "instanceID": 31564
                }
            ],
            "growthStageNumber": 2
        },
        {
            "growthStageSprites": [
                {
                    "instanceID": 31566
                },
                {
                    "instanceID": 31568
                }
            ],
            "growthStageNumber": 3
        },
        {
            "growthStageSprites": [
                {
                    "instanceID": 31570
                },
                {
                    "instanceID": 31572
                }
            ],
            "growthStageNumber": 4
        }
    ],
    "lastLogin": "2026-02-06T15:31:25.5161770+02:00"
}