{
    "isPlanted": true,
    "minYield": 1,
    "maxYield": 5,
    "currentStageNeedsWater": false,
    "currentStageProgress": 4,
    "minutesSinceLastStage": 0.0,
    "numStagesWatered": 0,
    "itemAssetName": "Grepa berry",
    "berryItem": {
        "instanceID": 26342
    },
    "treeIndex": 21,
    "minutesPerStage": 180,
    "spriteData": [
        {
            "growthStageSprites": [
                {
                    "instanceID": 32474
                },
                {
                    "instanceID": 32474
                }
            ],
            "growthStageNumber": 0
        },
        {
            "growthStageSprites": [
                {
                    "instanceID": 32476
                },
                {
                    "instanceID": 32478
                }
            ],
            "growthStageNumber": 1
        },
        {
            "growthStageSprites": [
                {
                    "instanceID": 32528
                },
                {
                    "instanceID": 32530
                }
            ],
            "growthStageNumber": 2
        },
        {
            "growthStageSprites": [
                {
                    "instanceID": 32532
                },
                {
                    "instanceID": 32534
                }
            ],
            "growthStageNumber": 3
        },
        {
            "growthStageSprites": [
                {
                    "instanceID": 32536
                },
                {
                    "instanceID": 32538
                }
            ],
            "growthStageNumber": 4
        }
    ],
    "lastLogin": "2025-11-30T11:24:22.6089950+02:00"
}