{
    "isPlanted": true,
    "minYield": 2,
    "maxYield": 5,
    "currentStageNeedsWater": false,
    "currentStageProgress": 4,
    "minutesSinceLastStage": 0.0,
    "numStagesWatered": 0,
    "itemAssetName": "Rawst berry",
    "berryItem": {
        "instanceID": 26050
    },
    "treeIndex": 2,
    "minutesPerStage": 45,
    "spriteData": [
        {
            "growthStageSprites": [
                {
                    "instanceID": 32798
                },
                {
                    "instanceID": 32798
                }
            ],
            "growthStageNumber": 0
        },
        {
            "growthStageSprites": [
                {
                    "instanceID": 32800
                },
                {
                    "instanceID": 32802
                }
            ],
            "growthStageNumber": 1
        },
        {
            "growthStageSprites": [
                {
                    "instanceID": 33452
                },
                {
                    "instanceID": 33454
                }
            ],
            "growthStageNumber": 2
        },
        {
            "growthStageSprites": [
                {
                    "instanceID": 33456
                },
                {
                    "instanceID": 33458
                }
            ],
            "growthStageNumber": 3
        },
        {
            "growthStageSprites": [
                {
                    "instanceID": 33460
                },
                {
                    "instanceID": 33462
                }
            ],
            "growthStageNumber": 4
        }
    ],
    "lastLogin": "2026-04-29T15:02:52.0798180+02:00"
}