{
    "isPlanted": true,
    "minYield": 2,
    "maxYield": 5,
    "currentStageNeedsWater": false,
    "currentStageProgress": 4,
    "minutesSinceLastStage": 0.0,
    "numStagesWatered": 0,
    "itemAssetName": "Sitrus berry",
    "berryItem": {
        "instanceID": 25940
    },
    "treeIndex": 33,
    "minutesPerStage": 90,
    "spriteData": [
        {
            "growthStageSprites": [
                {
                    "instanceID": 32294
                },
                {
                    "instanceID": 32294
                }
            ],
            "growthStageNumber": 0
        },
        {
            "growthStageSprites": [
                {
                    "instanceID": 32296
                },
                {
                    "instanceID": 32298
                }
            ],
            "growthStageNumber": 1
        },
        {
            "growthStageSprites": [
                {
                    "instanceID": 32594
                },
                {
                    "instanceID": 32596
                }
            ],
            "growthStageNumber": 2
        },
        {
            "growthStageSprites": [
                {
                    "instanceID": 32598
                },
                {
                    "instanceID": 32600
                }
            ],
            "growthStageNumber": 3
        },
        {
            "growthStageSprites": [
                {
                    "instanceID": 32602
                },
                {
                    "instanceID": 32604
                }
            ],
            "growthStageNumber": 4
        }
    ],
    "lastLogin": "2025-10-31T11:45:28.3928540+02:00"
}