{
    "isPlanted": true,
    "minYield": 2,
    "maxYield": 5,
    "currentStageNeedsWater": false,
    "currentStageProgress": 4,
    "minutesSinceLastStage": 0.0,
    "numStagesWatered": 0,
    "itemAssetName": "Cherri berry",
    "berryItem": {
        "instanceID": 26076
    },
    "minutesPerStage": 45,
    "spriteData": [
        {
            "growthStageSprites": [
                {
                    "instanceID": 32612
                },
                {
                    "instanceID": 32612
                }
            ],
            "growthStageNumber": 0
        },
        {
            "growthStageSprites": [
                {
                    "instanceID": 32614
                },
                {
                    "instanceID": 32616
                }
            ],
            "growthStageNumber": 1
        },
        {
            "growthStageSprites": [
                {
                    "instanceID": 32630
                },
                {
                    "instanceID": 32632
                }
            ],
            "growthStageNumber": 2
        },
        {
            "growthStageSprites": [
                {
                    "instanceID": 32634
                },
                {
                    "instanceID": 32636
                }
            ],
            "growthStageNumber": 3
        },
        {
            "growthStageSprites": [
                {
                    "instanceID": 32638
                },
                {
                    "instanceID": 32640
                }
            ],
            "growthStageNumber": 4
        }
    ],
    "soilIndex": 0,
    "lastLogin": "2026-06-04T11:38:52.8333470+02:00"
}